{
  "ComputerSystem": {
    "CimClass": {
      "CimSuperClassName": "CIM_UnitaryComputerSystem",
      "CimSuperClass": "ROOT/cimv2:CIM_UnitaryComputerSystem",
      "CimClassProperties": "Caption Description InstallDate Name Status CreationClassName NameFormat PrimaryOwnerContact PrimaryOwnerName Roles InitialLoadInfo LastLoadInfo PowerManagementCapabilities PowerManagementSupported PowerState ResetCapability AdminPasswordStatus AutomaticManagedPagefile AutomaticResetBootOption AutomaticResetCapability BootOptionOnLimit BootOptionOnWatchDog BootROMSupported BootStatus BootupState ChassisBootupState ChassisSKUNumber CurrentTimeZone DaylightInEffect DNSHostName Domain DomainRole EnableDaylightSavingsTime FrontPanelResetStatus HypervisorPresent InfraredSupported KeyboardPasswordStatus Manufacturer Model NetworkServerModeEnabled NumberOfLogicalProcessors NumberOfProcessors OEMLogoBitmap OEMStringArray PartOfDomain PauseAfterReset PCSystemType PCSystemTypeEx PowerOnPasswordStatus PowerSupplyState ResetCount ResetLimit SupportContactDescription SystemFamily SystemSKUNumber SystemStartupDelay SystemStartupOptions SystemStartupSetting SystemType ThermalState TotalPhysicalMemory UserName WakeUpType Workgroup",
      "CimClassQualifiers": "Locale = 1033 UUID = \"{8502C4B0-5FBB-11D2-AAC1-006008C78BC7}\" dynamic = True provider = \"CIMWin32\" SupportsUpdate = True",
      "CimClassMethods": "SetPowerState Rename JoinDomainOrWorkgroup UnjoinDomainOrWorkgroup",
      "CimSystemProperties": "Microsoft.Management.Infrastructure.CimSystemProperties"
    },
    "CimInstanceProperties": [
      "Caption = \"UVMINIAX\"",
      "Description = \"AT/AT COMPATIBLE\"",
      "InstallDate",
      "Name = \"UVMINIAX\"",
      "Status = \"OK\"",
      "CreationClassName = \"Win32_ComputerSystem\"",
      "NameFormat",
      "PrimaryOwnerContact",
      "PrimaryOwnerName = \"uv\"",
      "Roles = ...",
      "InitialLoadInfo",
      "LastLoadInfo",
      "PowerManagementCapabilities",
      "PowerManagementSupported",
      "PowerState = 0",
      "ResetCapability = 1",
      "AdminPasswordStatus = 3",
      "AutomaticManagedPagefile = True",
      "AutomaticResetBootOption = True",
      "AutomaticResetCapability = True",
      "BootOptionOnLimit",
      "BootOptionOnWatchDog",
      "BootROMSupported = True",
      "BootStatus = ...",
      "BootupState = \"Normal boot\"",
      "ChassisBootupState = 3",
      "ChassisSKUNumber = \"Default string\"",
      "CurrentTimeZone = 60",
      "DaylightInEffect = False",
      "DNSHostName = \"UVMINIAX\"",
      "Domain = \"WORKGROUP\"",
      "DomainRole = 0",
      "EnableDaylightSavingsTime = True",
      "FrontPanelResetStatus = 3",
      "HypervisorPresent = True",
      "InfraredSupported = False",
      "KeyboardPasswordStatus = 3",
      "Manufacturer = \"GEEKOM\"",
      "Model = \"AX8Pro\"",
      "NetworkServerModeEnabled = True",
      "NumberOfLogicalProcessors = 16",
      "NumberOfProcessors = 1",
      "OEMLogoBitmap",
      "OEMStringArray = ...",
      "PartOfDomain = False",
      "PauseAfterReset = -1",
      "PCSystemType = 2",
      "PCSystemTypeEx = 2",
      "PowerOnPasswordStatus = 3",
      "PowerSupplyState = 3",
      "ResetCount = -1",
      "ResetLimit = -1",
      "SupportContactDescription",
      "SystemFamily = \"AX** Pro Series\"",
      "SystemSKUNumber = \"GEEKOM AX8 Pro\"",
      "SystemStartupDelay",
      "SystemStartupOptions",
      "SystemStartupSetting",
      "SystemType = \"x64-based PC\"",
      "ThermalState = 3",
      "TotalPhysicalMemory = 33590505472",
      "UserName = \"UVMINIAX\\uv\"",
      "WakeUpType = 6",
      "Workgroup = \"WORKGROUP\""
    ],
    "CimSystemProperties": {
      "Namespace": "root/cimv2",
      "ServerName": "UVMINIAX",
      "ClassName": "Win32_ComputerSystem",
      "Path": null
    },
    "Caption": "UVMINIAX",
    "Description": "AT/AT COMPATIBLE",
    "InstallDate": null,
    "Name": "UVMINIAX",
    "Status": "OK",
    "CreationClassName": "Win32_ComputerSystem",
    "NameFormat": null,
    "PrimaryOwnerContact": null,
    "PrimaryOwnerName": "uv",
    "Roles": [
      "LM_Workstation",
      "LM_Server",
      "NT"
    ],
    "InitialLoadInfo": null,
    "LastLoadInfo": null,
    "PowerManagementCapabilities": null,
    "PowerManagementSupported": null,
    "PowerState": 0,
    "ResetCapability": 1,
    "AdminPasswordStatus": 3,
    "AutomaticManagedPagefile": true,
    "AutomaticResetBootOption": true,
    "AutomaticResetCapability": true,
    "BootOptionOnLimit": null,
    "BootOptionOnWatchDog": null,
    "BootROMSupported": true,
    "BootStatus": [
      0,
      0,
      0,
      44,
      9,
      9,
      0,
      0,
      0,
      1
    ],
    "BootupState": "Normal boot",
    "ChassisBootupState": 3,
    "ChassisSKUNumber": "Default string",
    "CurrentTimeZone": 60,
    "DaylightInEffect": false,
    "DNSHostName": "UVMINIAX",
    "Domain": "WORKGROUP",
    "DomainRole": 0,
    "EnableDaylightSavingsTime": true,
    "FrontPanelResetStatus": 3,
    "HypervisorPresent": true,
    "InfraredSupported": false,
    "KeyboardPasswordStatus": 3,
    "Manufacturer": "GEEKOM",
    "Model": "AX8Pro",
    "NetworkServerModeEnabled": true,
    "NumberOfLogicalProcessors": 16,
    "NumberOfProcessors": 1,
    "OEMLogoBitmap": null,
    "OEMStringArray": [
      "Default string"
    ],
    "PartOfDomain": false,
    "PauseAfterReset": -1,
    "PCSystemType": 2,
    "PCSystemTypeEx": 2,
    "PowerOnPasswordStatus": 3,
    "PowerSupplyState": 3,
    "ResetCount": -1,
    "ResetLimit": -1,
    "SupportContactDescription": null,
    "SystemFamily": "AX** Pro Series",
    "SystemSKUNumber": "GEEKOM AX8 Pro",
    "SystemStartupDelay": null,
    "SystemStartupOptions": null,
    "SystemStartupSetting": null,
    "SystemType": "x64-based PC",
    "ThermalState": 3,
    "TotalPhysicalMemory": 33590505472,
    "UserName": "UVMINIAX\\uv",
    "WakeUpType": 6,
    "Workgroup": "WORKGROUP",
    "PSComputerName": null
  },
  "BIOS": {
    "CimClass": {
      "CimSuperClassName": "CIM_BIOSElement",
      "CimSuperClass": "ROOT/cimv2:CIM_BIOSElement",
      "CimClassProperties": "Caption Description InstallDate Name Status BuildNumber CodeSet IdentificationCode LanguageEdition Manufacturer OtherTargetOS SerialNumber SoftwareElementID SoftwareElementState TargetOperatingSystem Version PrimaryBIOS BiosCharacteristics BIOSVersion CurrentLanguage EmbeddedControllerMajorVersion EmbeddedControllerMinorVersion InstallableLanguages ListOfLanguages ReleaseDate SMBIOSBIOSVersion SMBIOSMajorVersion SMBIOSMinorVersion SMBIOSPresent SystemBiosMajorVersion SystemBiosMinorVersion",
      "CimClassQualifiers": "Locale = 1033 UUID = \"{8502C4E1-5FBB-11D2-AAC1-006008C78BC7}\" dynamic = True provider = \"CIMWin32\"",
      "CimClassMethods": "",
      "CimSystemProperties": "Microsoft.Management.Infrastructure.CimSystemProperties"
    },
    "CimInstanceProperties": [
      "Caption = \"0.45\"",
      "Description = \"0.45\"",
      "InstallDate",
      "Name = \"0.45\"",
      "Status = \"OK\"",
      "BuildNumber",
      "CodeSet",
      "IdentificationCode",
      "LanguageEdition",
      "Manufacturer = \"American Megatrends International, LLC....",
      "OtherTargetOS",
      "SerialNumber = \"5201816C24290080\"",
      "SoftwareElementID = \"0.45\"",
      "SoftwareElementState = 3",
      "TargetOperatingSystem = 0",
      "Version = \"ALASKA - 1072009\"",
      "PrimaryBIOS = True",
      "BiosCharacteristics = ...",
      "BIOSVersion = ...",
      "CurrentLanguage = \"en?US?iso8859-1\"",
      "EmbeddedControllerMajorVersion = 0",
      "EmbeddedControllerMinorVersion = 92",
      "InstallableLanguages = 1",
      "ListOfLanguages = ...",
      "ReleaseDate = 07/04/2024 02:00:00",
      "SMBIOSBIOSVersion = \"0.45\"",
      "SMBIOSMajorVersion = 3",
      "SMBIOSMinorVersion = 5",
      "SMBIOSPresent = True",
      "SystemBiosMajorVersion = 0",
      "SystemBiosMinorVersion = 45"
    ],
    "CimSystemProperties": {
      "Namespace": "root/cimv2",
      "ServerName": "UVMINIAX",
      "ClassName": "Win32_BIOS",
      "Path": null
    },
    "Caption": "0.45",
    "Description": "0.45",
    "InstallDate": null,
    "Name": "0.45",
    "Status": "OK",
    "BuildNumber": null,
    "CodeSet": null,
    "IdentificationCode": null,
    "LanguageEdition": null,
    "Manufacturer": "American Megatrends International, LLC.",
    "OtherTargetOS": null,
    "SerialNumber": "5201816C24290080",
    "SoftwareElementID": "0.45",
    "SoftwareElementState": 3,
    "TargetOperatingSystem": 0,
    "Version": "ALASKA - 1072009",
    "PrimaryBIOS": true,
    "BiosCharacteristics": [
      7,
      11,
      12,
      15,
      16,
      17,
      19,
      32,
      40,
      42,
      43
    ],
    "BIOSVersion": [
      "ALASKA - 1072009",
      "0.45",
      "American Megatrends - 5001D"
    ],
    "CurrentLanguage": "en|US|iso8859-1",
    "EmbeddedControllerMajorVersion": 0,
    "EmbeddedControllerMinorVersion": 92,
    "InstallableLanguages": 1,
    "ListOfLanguages": [
      "en|US|iso8859-1"
    ],
    "ReleaseDate": "2024-04-07T02:00:00+02:00",
    "SMBIOSBIOSVersion": "0.45",
    "SMBIOSMajorVersion": 3,
    "SMBIOSMinorVersion": 5,
    "SMBIOSPresent": true,
    "SystemBiosMajorVersion": 0,
    "SystemBiosMinorVersion": 45,
    "PSComputerName": null
  },
  "CPU": {
    "CimClass": {
      "CimSuperClassName": "CIM_Processor",
      "CimSuperClass": "ROOT/cimv2:CIM_Processor",
      "CimClassProperties": "Caption Description InstallDate Name Status Availability ConfigManagerErrorCode ConfigManagerUserConfig CreationClassName DeviceID ErrorCleared ErrorDescription LastErrorCode PNPDeviceID PowerManagementCapabilities PowerManagementSupported StatusInfo SystemCreationClassName SystemName AddressWidth CurrentClockSpeed DataWidth Family LoadPercentage MaxClockSpeed OtherFamilyDescription Role Stepping UniqueId UpgradeMethod Architecture AssetTag Characteristics CpuStatus CurrentVoltage ExtClock L2CacheSize L2CacheSpeed L3CacheSize L3CacheSpeed Level Manufacturer NumberOfCores NumberOfEnabledCore NumberOfLogicalProcessors PartNumber ProcessorId ProcessorType Revision SecondLevelAddressTranslationExtensions SerialNumber SocketDesignation ThreadCount Version VirtualizationFirmwareEnabled VMMonitorModeExtensions VoltageCaps",
      "CimClassQualifiers": "Locale = 1033 UUID = \"{8502C4BB-5FBB-11D2-AAC1-006008C78BC7}\" dynamic = True provider = \"CIMWin32\"",
      "CimClassMethods": "SetPowerState Reset",
      "CimSystemProperties": "Microsoft.Management.Infrastructure.CimSystemProperties"
    },
    "CimInstanceProperties": [
      "Caption = \"AMD64 Family 25 Model 117 Stepping 2\"",
      "Description = \"AMD64 Family 25 Model 117 Stepping 2\"",
      "InstallDate",
      "Name = \"AMD Ryzen 9 8945HS w/ Radeon 780M Graph...",
      "Status = \"OK\"",
      "Availability = 3",
      "ConfigManagerErrorCode",
      "ConfigManagerUserConfig",
      "CreationClassName = \"Win32_Processor\"",
      "DeviceID = \"CPU0\"",
      "ErrorCleared",
      "ErrorDescription",
      "LastErrorCode",
      "PNPDeviceID",
      "PowerManagementCapabilities",
      "PowerManagementSupported = False",
      "StatusInfo = 3",
      "SystemCreationClassName = \"Win32_ComputerSystem\"",
      "SystemName = \"UVMINIAX\"",
      "AddressWidth = 64",
      "CurrentClockSpeed = 4001",
      "DataWidth = 64",
      "Family = 107",
      "LoadPercentage = 17",
      "MaxClockSpeed = 4001",
      "OtherFamilyDescription",
      "Role = \"CPU\"",
      "Stepping = \"2\"",
      "UniqueId",
      "UpgradeMethod = 6",
      "Architecture = 9",
      "AssetTag = \"Unknown\"",
      "Characteristics = 252",
      "CpuStatus = 1",
      "CurrentVoltage = 12",
      "ExtClock = 100",
      "L2CacheSize = 8192",
      "L2CacheSpeed",
      "L3CacheSize = 16384",
      "L3CacheSpeed = 0",
      "Level = 25",
      "Manufacturer = \"AuthenticAMD\"",
      "NumberOfCores = 8",
      "NumberOfEnabledCore = 8",
      "NumberOfLogicalProcessors = 16",
      "PartNumber = \"Unknown\"",
      "ProcessorId = \"178BFBFF00A70F52\"",
      "ProcessorType = 3",
      "Revision = 29954",
      "SecondLevelAddressTranslationExtensions = False",
      "SerialNumber = \"Unknown\"",
      "SocketDesignation = \"FP8\"",
      "ThreadCount = 16",
      "Version = \"Model 5, Stepping 2\"",
      "VirtualizationFirmwareEnabled = True",
      "VMMonitorModeExtensions = False",
      "VoltageCaps"
    ],
    "CimSystemProperties": {
      "Namespace": "root/cimv2",
      "ServerName": "UVMINIAX",
      "ClassName": "Win32_Processor",
      "Path": null
    },
    "Caption": "AMD64 Family 25 Model 117 Stepping 2",
    "Description": "AMD64 Family 25 Model 117 Stepping 2",
    "InstallDate": null,
    "Name": "AMD Ryzen 9 8945HS w/ Radeon 780M Graphics",
    "Status": "OK",
    "Availability": 3,
    "ConfigManagerErrorCode": null,
    "ConfigManagerUserConfig": null,
    "CreationClassName": "Win32_Processor",
    "DeviceID": "CPU0",
    "ErrorCleared": null,
    "ErrorDescription": null,
    "LastErrorCode": null,
    "PNPDeviceID": null,
    "PowerManagementCapabilities": null,
    "PowerManagementSupported": false,
    "StatusInfo": 3,
    "SystemCreationClassName": "Win32_ComputerSystem",
    "SystemName": "UVMINIAX",
    "AddressWidth": 64,
    "CurrentClockSpeed": 4001,
    "DataWidth": 64,
    "Family": 107,
    "LoadPercentage": 17,
    "MaxClockSpeed": 4001,
    "OtherFamilyDescription": null,
    "Role": "CPU",
    "Stepping": "2",
    "UniqueId": null,
    "UpgradeMethod": 6,
    "Architecture": 9,
    "AssetTag": "Unknown",
    "Characteristics": 252,
    "CpuStatus": 1,
    "CurrentVoltage": 12,
    "ExtClock": 100,
    "L2CacheSize": 8192,
    "L2CacheSpeed": null,
    "L3CacheSize": 16384,
    "L3CacheSpeed": 0,
    "Level": 25,
    "Manufacturer": "AuthenticAMD",
    "NumberOfCores": 8,
    "NumberOfEnabledCore": 8,
    "NumberOfLogicalProcessors": 16,
    "PartNumber": "Unknown",
    "ProcessorId": "178BFBFF00A70F52",
    "ProcessorType": 3,
    "Revision": 29954,
    "SecondLevelAddressTranslationExtensions": false,
    "SerialNumber": "Unknown",
    "SocketDesignation": "FP8",
    "ThreadCount": 16,
    "Version": "Model 5, Stepping 2",
    "VirtualizationFirmwareEnabled": true,
    "VMMonitorModeExtensions": false,
    "VoltageCaps": null,
    "PSComputerName": null
  },
  "BaseBoard": {
    "CimClass": {
      "CimSuperClassName": "CIM_Card",
      "CimSuperClass": "ROOT/cimv2:CIM_Card",
      "CimClassProperties": "Caption Description InstallDate Name Status CreationClassName Manufacturer Model OtherIdentifyingInfo PartNumber PoweredOn SerialNumber SKU Tag Version Depth Height HotSwappable Removable Replaceable Weight Width HostingBoard RequirementsDescription RequiresDaughterBoard SlotLayout SpecialRequirements ConfigOptions Product",
      "CimClassQualifiers": "Locale = 1033 UUID = \"{FAF76B95-798C-11D2-AAD1-006008C78BC7}\" dynamic = True provider = \"CIMWin32\"",
      "CimClassMethods": "IsCompatible",
      "CimSystemProperties": "Microsoft.Management.Infrastructure.CimSystemProperties"
    },
    "CimInstanceProperties": [
      "Caption = \"Base Board\"",
      "Description = \"Base Board\"",
      "InstallDate",
      "Name = \"Base Board\"",
      "Status = \"OK\"",
      "CreationClassName = \"Win32_BaseBoard\"",
      "Manufacturer = \"Default string\"",
      "Model",
      "OtherIdentifyingInfo",
      "PartNumber",
      "PoweredOn = True",
      "SerialNumber = \"NUCRB021924B12G1241600830\"",
      "SKU",
      "Tag = \"Base Board\"",
      "Version = \"Default string\"",
      "Depth",
      "Height",
      "HotSwappable = False",
      "Removable = False",
      "Replaceable = True",
      "Weight",
      "Width",
      "HostingBoard = True",
      "RequirementsDescription",
      "RequiresDaughterBoard = False",
      "SlotLayout",
      "SpecialRequirements",
      "ConfigOptions = ...",
      "Product = \"AX8 Pro\""
    ],
    "CimSystemProperties": {
      "Namespace": "root/cimv2",
      "ServerName": "UVMINIAX",
      "ClassName": "Win32_BaseBoard",
      "Path": null
    },
    "Caption": "Base Board",
    "Description": "Base Board",
    "InstallDate": null,
    "Name": "Base Board",
    "Status": "OK",
    "CreationClassName": "Win32_BaseBoard",
    "Manufacturer": "Default string",
    "Model": null,
    "OtherIdentifyingInfo": null,
    "PartNumber": null,
    "PoweredOn": true,
    "SerialNumber": "NUCRB021924B12G1241600830",
    "SKU": null,
    "Tag": "Base Board",
    "Version": "Default string",
    "Depth": null,
    "Height": null,
    "HotSwappable": false,
    "Removable": false,
    "Replaceable": true,
    "Weight": null,
    "Width": null,
    "HostingBoard": true,
    "RequirementsDescription": null,
    "RequiresDaughterBoard": false,
    "SlotLayout": null,
    "SpecialRequirements": null,
    "ConfigOptions": [
      "Default string"
    ],
    "Product": "AX8 Pro",
    "PSComputerName": null
  },
  "VideoController": {
    "CimClass": {
      "CimSuperClassName": "CIM_PCVideoController",
      "CimSuperClass": "ROOT/cimv2:CIM_PCVideoController",
      "CimClassProperties": "Caption Description InstallDate Name Status Availability ConfigManagerErrorCode ConfigManagerUserConfig CreationClassName DeviceID ErrorCleared ErrorDescription LastErrorCode PNPDeviceID PowerManagementCapabilities PowerManagementSupported StatusInfo SystemCreationClassName SystemName MaxNumberControlled ProtocolSupported TimeOfLastReset AcceleratorCapabilities CapabilityDescriptions CurrentBitsPerPixel CurrentHorizontalResolution CurrentNumberOfColors CurrentNumberOfColumns CurrentNumberOfRows CurrentRefreshRate CurrentScanMode CurrentVerticalResolution MaxMemorySupported MaxRefreshRate MinRefreshRate NumberOfVideoPages VideoMemoryType VideoProcessor NumberOfColorPlanes VideoArchitecture VideoMode AdapterCompatibility AdapterDACType AdapterRAM ColorTableEntries DeviceSpecificPens DitherType DriverDate DriverVersion ICMIntent ICMMethod InfFilename InfSection InstalledDisplayDrivers Monochrome ReservedSystemPaletteEntries SpecificationVersion SystemPaletteEntries VideoModeDescription",
      "CimClassQualifiers": "Locale = 1033 UUID = \"{1008CCF1-7BFF-11D2-AAD2-006008C78BC7}\" dynamic = True provider = \"CIMWin32\"",
      "CimClassMethods": "SetPowerState Reset",
      "CimSystemProperties": "Microsoft.Management.Infrastructure.CimSystemProperties"
    },
    "CimInstanceProperties": [
      "Caption = \"AMD Radeon 780M Graphics\"",
      "Description = \"AMD Radeon 780M Graphics\"",
      "InstallDate",
      "Name = \"AMD Radeon 780M Graphics\"",
      "Status = \"OK\"",
      "Availability = 3",
      "ConfigManagerErrorCode = 0",
      "ConfigManagerUserConfig = False",
      "CreationClassName = \"Win32_VideoController\"",
      "DeviceID = \"VideoController1\"",
      "ErrorCleared",
      "ErrorDescription",
      "LastErrorCode",
      "PNPDeviceID = \"PCI\\VEN_1002&DEV_1900&SUBSYS_01241002&R...",
      "PowerManagementCapabilities",
      "PowerManagementSupported",
      "StatusInfo",
      "SystemCreationClassName = \"Win32_ComputerSystem\"",
      "SystemName = \"UVMINIAX\"",
      "MaxNumberControlled",
      "ProtocolSupported",
      "TimeOfLastReset",
      "AcceleratorCapabilities",
      "CapabilityDescriptions",
      "CurrentBitsPerPixel = 32",
      "CurrentHorizontalResolution = 3840",
      "CurrentNumberOfColors = 4294967296",
      "CurrentNumberOfColumns = 0",
      "CurrentNumberOfRows = 0",
      "CurrentRefreshRate = 59",
      "CurrentScanMode = 4",
      "CurrentVerticalResolution = 2160",
      "MaxMemorySupported",
      "MaxRefreshRate = 75",
      "MinRefreshRate = 23",
      "NumberOfVideoPages",
      "VideoMemoryType = 2",
      "VideoProcessor = \"AMD Radeon Graphics Processor (0x1900)\"",
      "NumberOfColorPlanes",
      "VideoArchitecture = 5",
      "VideoMode",
      "AdapterCompatibility = \"Advanced Micro Devices, Inc.\"",
      "AdapterDACType = \"Internal DAC(400MHz)\"",
      "AdapterRAM = 536870912",
      "ColorTableEntries",
      "DeviceSpecificPens",
      "DitherType = 0",
      "DriverDate = 27/08/2024 02:00:00",
      "DriverVersion = \"32.0.11027.1003\"",
      "ICMIntent",
      "ICMMethod",
      "InfFilename = \"oem98.inf\"",
      "InfSection = \"ati2mtag_Phoenix\"",
      "InstalledDisplayDrivers = \"C:\\Windows\\System32\\DriverStore\\FileRep...",
      "Monochrome = False",
      "ReservedSystemPaletteEntries",
      "SpecificationVersion",
      "SystemPaletteEntries",
      "VideoModeDescription = \"3840 x 2160 x 4294967296 colors\""
    ],
    "CimSystemProperties": {
      "Namespace": "root/cimv2",
      "ServerName": "UVMINIAX",
      "ClassName": "Win32_VideoController",
      "Path": null
    },
    "Caption": "AMD Radeon 780M Graphics",
    "Description": "AMD Radeon 780M Graphics",
    "InstallDate": null,
    "Name": "AMD Radeon 780M Graphics",
    "Status": "OK",
    "Availability": 3,
    "ConfigManagerErrorCode": 0,
    "ConfigManagerUserConfig": false,
    "CreationClassName": "Win32_VideoController",
    "DeviceID": "VideoController1",
    "ErrorCleared": null,
    "ErrorDescription": null,
    "LastErrorCode": null,
    "PNPDeviceID": "PCI\\VEN_1002&DEV_1900&SUBSYS_01241002&REV_C4\\4&98C338A&0&0041",
    "PowerManagementCapabilities": null,
    "PowerManagementSupported": null,
    "StatusInfo": null,
    "SystemCreationClassName": "Win32_ComputerSystem",
    "SystemName": "UVMINIAX",
    "MaxNumberControlled": null,
    "ProtocolSupported": null,
    "TimeOfLastReset": null,
    "AcceleratorCapabilities": null,
    "CapabilityDescriptions": null,
    "CurrentBitsPerPixel": 32,
    "CurrentHorizontalResolution": 3840,
    "CurrentNumberOfColors": 4294967296,
    "CurrentNumberOfColumns": 0,
    "CurrentNumberOfRows": 0,
    "CurrentRefreshRate": 59,
    "CurrentScanMode": 4,
    "CurrentVerticalResolution": 2160,
    "MaxMemorySupported": null,
    "MaxRefreshRate": 75,
    "MinRefreshRate": 23,
    "NumberOfVideoPages": null,
    "VideoMemoryType": 2,
    "VideoProcessor": "AMD Radeon Graphics Processor (0x1900)",
    "NumberOfColorPlanes": null,
    "VideoArchitecture": 5,
    "VideoMode": null,
    "AdapterCompatibility": "Advanced Micro Devices, Inc.",
    "AdapterDACType": "Internal DAC(400MHz)",
    "AdapterRAM": 536870912,
    "ColorTableEntries": null,
    "DeviceSpecificPens": null,
    "DitherType": 0,
    "DriverDate": "2024-08-27T02:00:00+02:00",
    "DriverVersion": "32.0.11027.1003",
    "ICMIntent": null,
    "ICMMethod": null,
    "InfFilename": "oem98.inf",
    "InfSection": "ati2mtag_Phoenix",
    "InstalledDisplayDrivers": "C:\\Windows\\System32\\DriverStore\\FileRepository\\u0407412.inf_amd64_101d3d4e34955a9f\\B407018\\atidx9loader64.dll,C:\\Windows\\System32\\DriverStore\\FileRepository\\u0407412.inf_amd64_101d3d4e34955a9f\\B407018\\amdxx64.dll,C:\\Windows\\System32\\DriverStore\\FileRepository\\u0407412.inf_amd64_101d3d4e34955a9f\\B407018\\amdxx64.dll,C:\\Windows\\System32\\DriverStore\\FileRepository\\u0407412.inf_amd64_101d3d4e34955a9f\\B407018\\amdxc64.dll",
    "Monochrome": false,
    "ReservedSystemPaletteEntries": null,
    "SpecificationVersion": null,
    "SystemPaletteEntries": null,
    "VideoModeDescription": "3840 x 2160 x 4294967296 colors",
    "PSComputerName": null
  },
  "PhysicalMemory": [
    {
      "CimClass": "root/cimv2:Win32_PhysicalMemory",
      "CimInstanceProperties": "Caption = \"Physical Memory\" Description = \"Physical Memory\" InstallDate Name = \"Physical Memory\" Status CreationClassName = \"Win32_PhysicalMemory\" Manufacturer = \"Unknown\" Model OtherIdentifyingInfo PartNumber = \"CT16G56C46S5.M8B2   \" PoweredOn SerialNumber = \"E94A5EBC\" SKU Tag = \"Physical Memory 0\" Version HotSwappable Removable Replaceable FormFactor = 12 BankLabel = \"P0 CHANNEL A\" Capacity = 17179869184 DataWidth = 64 InterleavePosition MemoryType = 0 PositionInRow Speed = 5600 TotalWidth = 64 Attributes = 1 ConfiguredClockSpeed = 5600 ConfiguredVoltage = 1100 DeviceLocator = \"DIMM 0\" InterleaveDataDepth MaxVoltage = 1100 MinVoltage = 1100 SMBIOSMemoryType = 34 TypeDetail = 16512",
      "CimSystemProperties": "Microsoft.Management.Infrastructure.CimSystemProperties",
      "Caption": "Physical Memory",
      "Description": "Physical Memory",
      "InstallDate": null,
      "Name": "Physical Memory",
      "Status": null,
      "CreationClassName": "Win32_PhysicalMemory",
      "Manufacturer": "Unknown",
      "Model": null,
      "OtherIdentifyingInfo": null,
      "PartNumber": "CT16G56C46S5.M8B2   ",
      "PoweredOn": null,
      "SerialNumber": "E94A5EBC",
      "SKU": null,
      "Tag": "Physical Memory 0",
      "Version": null,
      "HotSwappable": null,
      "Removable": null,
      "Replaceable": null,
      "FormFactor": 12,
      "BankLabel": "P0 CHANNEL A",
      "Capacity": 17179869184,
      "DataWidth": 64,
      "InterleavePosition": null,
      "MemoryType": 0,
      "PositionInRow": null,
      "Speed": 5600,
      "TotalWidth": 64,
      "Attributes": 1,
      "ConfiguredClockSpeed": 5600,
      "ConfiguredVoltage": 1100,
      "DeviceLocator": "DIMM 0",
      "InterleaveDataDepth": null,
      "MaxVoltage": 1100,
      "MinVoltage": 1100,
      "SMBIOSMemoryType": 34,
      "TypeDetail": 16512,
      "PSComputerName": null
    },
    {
      "CimClass": "root/cimv2:Win32_PhysicalMemory",
      "CimInstanceProperties": "Caption = \"Physical Memory\" Description = \"Physical Memory\" InstallDate Name = \"Physical Memory\" Status CreationClassName = \"Win32_PhysicalMemory\" Manufacturer = \"Unknown\" Model OtherIdentifyingInfo PartNumber = \"CT16G56C46S5.M8B2   \" PoweredOn SerialNumber = \"E94A5EC3\" SKU Tag = \"Physical Memory 1\" Version HotSwappable Removable Replaceable FormFactor = 12 BankLabel = \"P0 CHANNEL B\" Capacity = 17179869184 DataWidth = 64 InterleavePosition MemoryType = 0 PositionInRow Speed = 5600 TotalWidth = 64 Attributes = 1 ConfiguredClockSpeed = 5600 ConfiguredVoltage = 1100 DeviceLocator = \"DIMM 0\" InterleaveDataDepth MaxVoltage = 1100 MinVoltage = 1100 SMBIOSMemoryType = 34 TypeDetail = 16512",
      "CimSystemProperties": "Microsoft.Management.Infrastructure.CimSystemProperties",
      "Caption": "Physical Memory",
      "Description": "Physical Memory",
      "InstallDate": null,
      "Name": "Physical Memory",
      "Status": null,
      "CreationClassName": "Win32_PhysicalMemory",
      "Manufacturer": "Unknown",
      "Model": null,
      "OtherIdentifyingInfo": null,
      "PartNumber": "CT16G56C46S5.M8B2   ",
      "PoweredOn": null,
      "SerialNumber": "E94A5EC3",
      "SKU": null,
      "Tag": "Physical Memory 1",
      "Version": null,
      "HotSwappable": null,
      "Removable": null,
      "Replaceable": null,
      "FormFactor": 12,
      "BankLabel": "P0 CHANNEL B",
      "Capacity": 17179869184,
      "DataWidth": 64,
      "InterleavePosition": null,
      "MemoryType": 0,
      "PositionInRow": null,
      "Speed": 5600,
      "TotalWidth": 64,
      "Attributes": 1,
      "ConfiguredClockSpeed": 5600,
      "ConfiguredVoltage": 1100,
      "DeviceLocator": "DIMM 0",
      "InterleaveDataDepth": null,
      "MaxVoltage": 1100,
      "MinVoltage": 1100,
      "SMBIOSMemoryType": 34,
      "TypeDetail": 16512,
      "PSComputerName": null
    }
  ],
  "DiskDrives": [
    {
      "CimClass": "root/cimv2:Win32_DiskDrive",
      "CimInstanceProperties": "Caption = \"Viper VP 4300L 2TB   SN08 SCSI Disk Dev... Description = \"Disk drive\" InstallDate Name = \"\\\\.\\PHYSICALDRIVE4\" Status = \"OK\" Availability ConfigManagerErrorCode = 0 ConfigManagerUserConfig = False CreationClassName = \"Win32_DiskDrive\" DeviceID = \"\\\\.\\PHYSICALDRIVE4\" ErrorCleared ErrorDescription LastErrorCode PNPDeviceID = \"SCSI\\DISK&VEN_VIPER_VP&PROD_4300L_2TB__... PowerManagementCapabilities PowerManagementSupported StatusInfo SystemCreationClassName = \"Win32_ComputerSystem\" SystemName = \"UVMINIAX\" Capabilities = ... CapabilityDescriptions = ... CompressionMethod DefaultBlockSize ErrorMethodology MaxBlockSize MaxMediaSize MinBlockSize NeedsCleaning NumberOfMediaSupported BytesPerSector = 512 FirmwareRevision = \"8202\" Index = 4 InterfaceType = \"SCSI\" Manufacturer = \"(Standard disk drives)\" MediaLoaded = True MediaType = \"External hard disk media\" Model = \"Viper VP 4300L 2TB   SN08 SCSI Disk Dev... Partitions = 1 SCSIBus = 0 SCSILogicalUnit = 0 SCSIPort = 5 SCSITargetId = 0 SectorsPerTrack = 63 SerialNumber = \"??D\" Signature Size = 2000396321280 TotalCylinders = 243201 TotalHeads = 255 TotalSectors = 3907024065 TotalTracks = 62016255 TracksPerCylinder = 255",
      "CimSystemProperties": "Microsoft.Management.Infrastructure.CimSystemProperties",
      "Caption": "Viper VP 4300L 2TB   SN08 SCSI Disk Device",
      "Description": "Disk drive",
      "InstallDate": null,
      "Name": "\\\\.\\PHYSICALDRIVE4",
      "Status": "OK",
      "Availability": null,
      "ConfigManagerErrorCode": 0,
      "ConfigManagerUserConfig": false,
      "CreationClassName": "Win32_DiskDrive",
      "DeviceID": "\\\\.\\PHYSICALDRIVE4",
      "ErrorCleared": null,
      "ErrorDescription": null,
      "LastErrorCode": null,
      "PNPDeviceID": "SCSI\\DISK&VEN_VIPER_VP&PROD_4300L_2TB___SN08\\8&1A2135A0&0&000000",
      "PowerManagementCapabilities": null,
      "PowerManagementSupported": null,
      "StatusInfo": null,
      "SystemCreationClassName": "Win32_ComputerSystem",
      "SystemName": "UVMINIAX",
      "Capabilities": "3 4",
      "CapabilityDescriptions": "Random Access Supports Writing",
      "CompressionMethod": null,
      "DefaultBlockSize": null,
      "ErrorMethodology": null,
      "MaxBlockSize": null,
      "MaxMediaSize": null,
      "MinBlockSize": null,
      "NeedsCleaning": null,
      "NumberOfMediaSupported": null,
      "BytesPerSector": 512,
      "FirmwareRevision": "8202",
      "Index": 4,
      "InterfaceType": "SCSI",
      "Manufacturer": "(Standard disk drives)",
      "MediaLoaded": true,
      "MediaType": "External hard disk media",
      "Model": "Viper VP 4300L 2TB   SN08 SCSI Disk Device",
      "Partitions": 1,
      "SCSIBus": 0,
      "SCSILogicalUnit": 0,
      "SCSIPort": 5,
      "SCSITargetId": 0,
      "SectorsPerTrack": 63,
      "SerialNumber": "\u001a\u0003D",
      "Signature": null,
      "Size": 2000396321280,
      "TotalCylinders": 243201,
      "TotalHeads": 255,
      "TotalSectors": 3907024065,
      "TotalTracks": 62016255,
      "TracksPerCylinder": 255,
      "PSComputerName": null
    },
    {
      "CimClass": "root/cimv2:Win32_DiskDrive",
      "CimInstanceProperties": "Caption = \"Generic STORAGE DEVICE USB Device\" Description = \"Disk drive\" InstallDate Name = \"\\\\.\\PHYSICALDRIVE1\" Status = \"OK\" Availability ConfigManagerErrorCode = 0 ConfigManagerUserConfig = False CreationClassName = \"Win32_DiskDrive\" DeviceID = \"\\\\.\\PHYSICALDRIVE1\" ErrorCleared ErrorDescription LastErrorCode PNPDeviceID = \"USBSTOR\\DISK&VEN_GENERIC&PROD_STORAGE_D... PowerManagementCapabilities PowerManagementSupported StatusInfo SystemCreationClassName = \"Win32_ComputerSystem\" SystemName = \"UVMINIAX\" Capabilities CapabilityDescriptions CompressionMethod DefaultBlockSize ErrorMethodology MaxBlockSize MaxMediaSize MinBlockSize NeedsCleaning NumberOfMediaSupported BytesPerSector FirmwareRevision = \"1532\" Index = 1 InterfaceType = \"USB\" Manufacturer = \"(Standard disk drives)\" MediaLoaded = True MediaType Model = \"Generic STORAGE DEVICE USB Device\" Partitions = 0 SCSIBus = 0 SCSILogicalUnit = 0 SCSIPort = 0 SCSITargetId = 0 SectorsPerTrack SerialNumber = \"000000001532\" Signature = 0 Size TotalCylinders TotalHeads TotalSectors TotalTracks TracksPerCylinder",
      "CimSystemProperties": "Microsoft.Management.Infrastructure.CimSystemProperties",
      "Caption": "Generic STORAGE DEVICE USB Device",
      "Description": "Disk drive",
      "InstallDate": null,
      "Name": "\\\\.\\PHYSICALDRIVE1",
      "Status": "OK",
      "Availability": null,
      "ConfigManagerErrorCode": 0,
      "ConfigManagerUserConfig": false,
      "CreationClassName": "Win32_DiskDrive",
      "DeviceID": "\\\\.\\PHYSICALDRIVE1",
      "ErrorCleared": null,
      "ErrorDescription": null,
      "LastErrorCode": null,
      "PNPDeviceID": "USBSTOR\\DISK&VEN_GENERIC&PROD_STORAGE_DEVICE&REV_1532\\000000001532&0",
      "PowerManagementCapabilities": null,
      "PowerManagementSupported": null,
      "StatusInfo": null,
      "SystemCreationClassName": "Win32_ComputerSystem",
      "SystemName": "UVMINIAX",
      "Capabilities": null,
      "CapabilityDescriptions": null,
      "CompressionMethod": null,
      "DefaultBlockSize": null,
      "ErrorMethodology": null,
      "MaxBlockSize": null,
      "MaxMediaSize": null,
      "MinBlockSize": null,
      "NeedsCleaning": null,
      "NumberOfMediaSupported": null,
      "BytesPerSector": null,
      "FirmwareRevision": "1532",
      "Index": 1,
      "InterfaceType": "USB",
      "Manufacturer": "(Standard disk drives)",
      "MediaLoaded": true,
      "MediaType": null,
      "Model": "Generic STORAGE DEVICE USB Device",
      "Partitions": 0,
      "SCSIBus": 0,
      "SCSILogicalUnit": 0,
      "SCSIPort": 0,
      "SCSITargetId": 0,
      "SectorsPerTrack": null,
      "SerialNumber": "000000001532",
      "Signature": 0,
      "Size": null,
      "TotalCylinders": null,
      "TotalHeads": null,
      "TotalSectors": null,
      "TotalTracks": null,
      "TracksPerCylinder": null,
      "PSComputerName": null
    },
    {
      "CimClass": "root/cimv2:Win32_DiskDrive",
      "CimInstanceProperties": "Caption = \"SanDisk SDSSDH31024G SCSI Disk Device\" Description = \"Disk drive\" InstallDate Name = \"\\\\.\\PHYSICALDRIVE8\" Status = \"OK\" Availability ConfigManagerErrorCode = 0 ConfigManagerUserConfig = False CreationClassName = \"Win32_DiskDrive\" DeviceID = \"\\\\.\\PHYSICALDRIVE8\" ErrorCleared ErrorDescription LastErrorCode PNPDeviceID = \"SCSI\\DISK&VEN_SANDISK&PROD_SDSSDH31024G... PowerManagementCapabilities PowerManagementSupported StatusInfo SystemCreationClassName = \"Win32_ComputerSystem\" SystemName = \"UVMINIAX\" Capabilities = ... CapabilityDescriptions = ... CompressionMethod DefaultBlockSize ErrorMethodology MaxBlockSize MaxMediaSize MinBlockSize NeedsCleaning NumberOfMediaSupported BytesPerSector = 512 FirmwareRevision = \"0301\" Index = 8 InterfaceType = \"SCSI\" Manufacturer = \"(Standard disk drives)\" MediaLoaded = True MediaType = \"External hard disk media\" Model = \"SanDisk SDSSDH31024G SCSI Disk Device\" Partitions = 1 SCSIBus = 0 SCSILogicalUnit = 0 SCSIPort = 3 SCSITargetId = 0 SectorsPerTrack = 63 SerialNumber = \"000000004984\" Signature Size = 1024203640320 TotalCylinders = 124519 TotalHeads = 255 TotalSectors = 2000397735 TotalTracks = 31752345 TracksPerCylinder = 255",
      "CimSystemProperties": "Microsoft.Management.Infrastructure.CimSystemProperties",
      "Caption": "SanDisk SDSSDH31024G SCSI Disk Device",
      "Description": "Disk drive",
      "InstallDate": null,
      "Name": "\\\\.\\PHYSICALDRIVE8",
      "Status": "OK",
      "Availability": null,
      "ConfigManagerErrorCode": 0,
      "ConfigManagerUserConfig": false,
      "CreationClassName": "Win32_DiskDrive",
      "DeviceID": "\\\\.\\PHYSICALDRIVE8",
      "ErrorCleared": null,
      "ErrorDescription": null,
      "LastErrorCode": null,
      "PNPDeviceID": "SCSI\\DISK&VEN_SANDISK&PROD_SDSSDH31024G\\8&9A25591&0&000000",
      "PowerManagementCapabilities": null,
      "PowerManagementSupported": null,
      "StatusInfo": null,
      "SystemCreationClassName": "Win32_ComputerSystem",
      "SystemName": "UVMINIAX",
      "Capabilities": "3 4",
      "CapabilityDescriptions": "Random Access Supports Writing",
      "CompressionMethod": null,
      "DefaultBlockSize": null,
      "ErrorMethodology": null,
      "MaxBlockSize": null,
      "MaxMediaSize": null,
      "MinBlockSize": null,
      "NeedsCleaning": null,
      "NumberOfMediaSupported": null,
      "BytesPerSector": 512,
      "FirmwareRevision": "0301",
      "Index": 8,
      "InterfaceType": "SCSI",
      "Manufacturer": "(Standard disk drives)",
      "MediaLoaded": true,
      "MediaType": "External hard disk media",
      "Model": "SanDisk SDSSDH31024G SCSI Disk Device",
      "Partitions": 1,
      "SCSIBus": 0,
      "SCSILogicalUnit": 0,
      "SCSIPort": 3,
      "SCSITargetId": 0,
      "SectorsPerTrack": 63,
      "SerialNumber": "000000004984",
      "Signature": null,
      "Size": 1024203640320,
      "TotalCylinders": 124519,
      "TotalHeads": 255,
      "TotalSectors": 2000397735,
      "TotalTracks": 31752345,
      "TracksPerCylinder": 255,
      "PSComputerName": null
    },
    {
      "CimClass": "root/cimv2:Win32_DiskDrive",
      "CimInstanceProperties": "Caption = \"CT1000MX 500SSD4 SCSI Disk Device\" Description = \"Disk drive\" InstallDate Name = \"\\\\.\\PHYSICALDRIVE9\" Status = \"OK\" Availability ConfigManagerErrorCode = 0 ConfigManagerUserConfig = False CreationClassName = \"Win32_DiskDrive\" DeviceID = \"\\\\.\\PHYSICALDRIVE9\" ErrorCleared ErrorDescription LastErrorCode PNPDeviceID = \"SCSI\\DISK&VEN_CT1000MX&PROD_500SSD4\\8&1... PowerManagementCapabilities PowerManagementSupported StatusInfo SystemCreationClassName = \"Win32_ComputerSystem\" SystemName = \"UVMINIAX\" Capabilities = ... CapabilityDescriptions = ... CompressionMethod DefaultBlockSize ErrorMethodology MaxBlockSize MaxMediaSize MinBlockSize NeedsCleaning NumberOfMediaSupported BytesPerSector = 512 FirmwareRevision = \"8202\" Index = 9 InterfaceType = \"SCSI\" Manufacturer = \"(Standard disk drives)\" MediaLoaded = True MediaType = \"External hard disk media\" Model = \"CT1000MX 500SSD4 SCSI Disk Device\" Partitions = 2 SCSIBus = 0 SCSILogicalUnit = 1 SCSIPort = 5 SCSITargetId = 0 SectorsPerTrack = 63 SerialNumber = \"??D\" Signature Size = 1000202273280 TotalCylinders = 121601 TotalHeads = 255 TotalSectors = 1953520065 TotalTracks = 31008255 TracksPerCylinder = 255",
      "CimSystemProperties": "Microsoft.Management.Infrastructure.CimSystemProperties",
      "Caption": "CT1000MX 500SSD4 SCSI Disk Device",
      "Description": "Disk drive",
      "InstallDate": null,
      "Name": "\\\\.\\PHYSICALDRIVE9",
      "Status": "OK",
      "Availability": null,
      "ConfigManagerErrorCode": 0,
      "ConfigManagerUserConfig": false,
      "CreationClassName": "Win32_DiskDrive",
      "DeviceID": "\\\\.\\PHYSICALDRIVE9",
      "ErrorCleared": null,
      "ErrorDescription": null,
      "LastErrorCode": null,
      "PNPDeviceID": "SCSI\\DISK&VEN_CT1000MX&PROD_500SSD4\\8&1A2135A0&0&000001",
      "PowerManagementCapabilities": null,
      "PowerManagementSupported": null,
      "StatusInfo": null,
      "SystemCreationClassName": "Win32_ComputerSystem",
      "SystemName": "UVMINIAX",
      "Capabilities": "3 4",
      "CapabilityDescriptions": "Random Access Supports Writing",
      "CompressionMethod": null,
      "DefaultBlockSize": null,
      "ErrorMethodology": null,
      "MaxBlockSize": null,
      "MaxMediaSize": null,
      "MinBlockSize": null,
      "NeedsCleaning": null,
      "NumberOfMediaSupported": null,
      "BytesPerSector": 512,
      "FirmwareRevision": "8202",
      "Index": 9,
      "InterfaceType": "SCSI",
      "Manufacturer": "(Standard disk drives)",
      "MediaLoaded": true,
      "MediaType": "External hard disk media",
      "Model": "CT1000MX 500SSD4 SCSI Disk Device",
      "Partitions": 2,
      "SCSIBus": 0,
      "SCSILogicalUnit": 1,
      "SCSIPort": 5,
      "SCSITargetId": 0,
      "SectorsPerTrack": 63,
      "SerialNumber": "\u001a\u0003D",
      "Signature": null,
      "Size": 1000202273280,
      "TotalCylinders": 121601,
      "TotalHeads": 255,
      "TotalSectors": 1953520065,
      "TotalTracks": 31008255,
      "TracksPerCylinder": 255,
      "PSComputerName": null
    },
    {
      "CimClass": "root/cimv2:Win32_DiskDrive",
      "CimInstanceProperties": "Caption = \"Samsung PSSD T7 Shield SCSI Disk Device... Description = \"Disk drive\" InstallDate Name = \"\\\\.\\PHYSICALDRIVE6\" Status = \"OK\" Availability ConfigManagerErrorCode = 0 ConfigManagerUserConfig = False CreationClassName = \"Win32_DiskDrive\" DeviceID = \"\\\\.\\PHYSICALDRIVE6\" ErrorCleared ErrorDescription LastErrorCode PNPDeviceID = \"SCSI\\DISK&VEN_SAMSUNG&PROD_PSSD_T7_SHIE... PowerManagementCapabilities PowerManagementSupported StatusInfo SystemCreationClassName = \"Win32_ComputerSystem\" SystemName = \"UVMINIAX\" Capabilities = ... CapabilityDescriptions = ... CompressionMethod DefaultBlockSize ErrorMethodology MaxBlockSize MaxMediaSize MinBlockSize NeedsCleaning NumberOfMediaSupported BytesPerSector = 512 FirmwareRevision = \"0   \" Index = 6 InterfaceType = \"SCSI\" Manufacturer = \"(Standard disk drives)\" MediaLoaded = True MediaType = \"External hard disk media\" Model = \"Samsung PSSD T7 Shield SCSI Disk Device... Partitions = 1 SCSIBus = 0 SCSILogicalUnit = 0 SCSIPort = 2 SCSITargetId = 0 SectorsPerTrack = 63 SerialNumber = \"R591202T0SNMY6S\" Signature Size = 2000396321280 TotalCylinders = 243201 TotalHeads = 255 TotalSectors = 3907024065 TotalTracks = 62016255 TracksPerCylinder = 255",
      "CimSystemProperties": "Microsoft.Management.Infrastructure.CimSystemProperties",
      "Caption": "Samsung PSSD T7 Shield SCSI Disk Device",
      "Description": "Disk drive",
      "InstallDate": null,
      "Name": "\\\\.\\PHYSICALDRIVE6",
      "Status": "OK",
      "Availability": null,
      "ConfigManagerErrorCode": 0,
      "ConfigManagerUserConfig": false,
      "CreationClassName": "Win32_DiskDrive",
      "DeviceID": "\\\\.\\PHYSICALDRIVE6",
      "ErrorCleared": null,
      "ErrorDescription": null,
      "LastErrorCode": null,
      "PNPDeviceID": "SCSI\\DISK&VEN_SAMSUNG&PROD_PSSD_T7_SHIELD\\8&30AD480D&0&000000",
      "PowerManagementCapabilities": null,
      "PowerManagementSupported": null,
      "StatusInfo": null,
      "SystemCreationClassName": "Win32_ComputerSystem",
      "SystemName": "UVMINIAX",
      "Capabilities": "3 4",
      "CapabilityDescriptions": "Random Access Supports Writing",
      "CompressionMethod": null,
      "DefaultBlockSize": null,
      "ErrorMethodology": null,
      "MaxBlockSize": null,
      "MaxMediaSize": null,
      "MinBlockSize": null,
      "NeedsCleaning": null,
      "NumberOfMediaSupported": null,
      "BytesPerSector": 512,
      "FirmwareRevision": "0   ",
      "Index": 6,
      "InterfaceType": "SCSI",
      "Manufacturer": "(Standard disk drives)",
      "MediaLoaded": true,
      "MediaType": "External hard disk media",
      "Model": "Samsung PSSD T7 Shield SCSI Disk Device",
      "Partitions": 1,
      "SCSIBus": 0,
      "SCSILogicalUnit": 0,
      "SCSIPort": 2,
      "SCSITargetId": 0,
      "SectorsPerTrack": 63,
      "SerialNumber": "R591202T0SNMY6S",
      "Signature": null,
      "Size": 2000396321280,
      "TotalCylinders": 243201,
      "TotalHeads": 255,
      "TotalSectors": 3907024065,
      "TotalTracks": 62016255,
      "TracksPerCylinder": 255,
      "PSComputerName": null
    },
    {
      "CimClass": "root/cimv2:Win32_DiskDrive",
      "CimInstanceProperties": "Caption = \"CT4000P3 SSD8 USB Device\" Description = \"Disk drive\" InstallDate Name = \"\\\\.\\PHYSICALDRIVE5\" Status = \"OK\" Availability ConfigManagerErrorCode = 0 ConfigManagerUserConfig = False CreationClassName = \"Win32_DiskDrive\" DeviceID = \"\\\\.\\PHYSICALDRIVE5\" ErrorCleared ErrorDescription LastErrorCode PNPDeviceID = \"USBSTOR\\DISK&VEN_CT4000P3&PROD_SSD8&REV... PowerManagementCapabilities PowerManagementSupported StatusInfo SystemCreationClassName = \"Win32_ComputerSystem\" SystemName = \"UVMINIAX\" Capabilities = ... CapabilityDescriptions = ... CompressionMethod DefaultBlockSize ErrorMethodology MaxBlockSize MaxMediaSize MinBlockSize NeedsCleaning NumberOfMediaSupported BytesPerSector = 512 FirmwareRevision = \"1.01\" Index = 5 InterfaceType = \"USB\" Manufacturer = \"(Standard disk drives)\" MediaLoaded = True MediaType = \"External hard disk media\" Model = \"CT4000P3 SSD8 USB Device\" Partitions = 1 SCSIBus = 0 SCSILogicalUnit = 0 SCSIPort = 0 SCSITargetId = 0 SectorsPerTrack = 63 SerialNumber = \"0000000000000000\" Signature Size = 4000784417280 TotalCylinders = 486401 TotalHeads = 255 TotalSectors = 7814032065 TotalTracks = 124032255 TracksPerCylinder = 255",
      "CimSystemProperties": "Microsoft.Management.Infrastructure.CimSystemProperties",
      "Caption": "CT4000P3 SSD8 USB Device",
      "Description": "Disk drive",
      "InstallDate": null,
      "Name": "\\\\.\\PHYSICALDRIVE5",
      "Status": "OK",
      "Availability": null,
      "ConfigManagerErrorCode": 0,
      "ConfigManagerUserConfig": false,
      "CreationClassName": "Win32_DiskDrive",
      "DeviceID": "\\\\.\\PHYSICALDRIVE5",
      "ErrorCleared": null,
      "ErrorDescription": null,
      "LastErrorCode": null,
      "PNPDeviceID": "USBSTOR\\DISK&VEN_CT4000P3&PROD_SSD8&REV_1.01\\0132680004C0&0",
      "PowerManagementCapabilities": null,
      "PowerManagementSupported": null,
      "StatusInfo": null,
      "SystemCreationClassName": "Win32_ComputerSystem",
      "SystemName": "UVMINIAX",
      "Capabilities": "3 4",
      "CapabilityDescriptions": "Random Access Supports Writing",
      "CompressionMethod": null,
      "DefaultBlockSize": null,
      "ErrorMethodology": null,
      "MaxBlockSize": null,
      "MaxMediaSize": null,
      "MinBlockSize": null,
      "NeedsCleaning": null,
      "NumberOfMediaSupported": null,
      "BytesPerSector": 512,
      "FirmwareRevision": "1.01",
      "Index": 5,
      "InterfaceType": "USB",
      "Manufacturer": "(Standard disk drives)",
      "MediaLoaded": true,
      "MediaType": "External hard disk media",
      "Model": "CT4000P3 SSD8 USB Device",
      "Partitions": 1,
      "SCSIBus": 0,
      "SCSILogicalUnit": 0,
      "SCSIPort": 0,
      "SCSITargetId": 0,
      "SectorsPerTrack": 63,
      "SerialNumber": "0000000000000000",
      "Signature": null,
      "Size": 4000784417280,
      "TotalCylinders": 486401,
      "TotalHeads": 255,
      "TotalSectors": 7814032065,
      "TotalTracks": 124032255,
      "TracksPerCylinder": 255,
      "PSComputerName": null
    },
    {
      "CimClass": "root/cimv2:Win32_DiskDrive",
      "CimInstanceProperties": "Caption = \"CT2000P3PSSD8\" Description = \"Disk drive\" InstallDate Name = \"\\\\.\\PHYSICALDRIVE0\" Status = \"OK\" Availability ConfigManagerErrorCode = 0 ConfigManagerUserConfig = False CreationClassName = \"Win32_DiskDrive\" DeviceID = \"\\\\.\\PHYSICALDRIVE0\" ErrorCleared ErrorDescription LastErrorCode PNPDeviceID = \"SCSI\\DISK&VEN_NVME&PROD_CT2000P3PSSD8\\5... PowerManagementCapabilities PowerManagementSupported StatusInfo SystemCreationClassName = \"Win32_ComputerSystem\" SystemName = \"UVMINIAX\" Capabilities = ... CapabilityDescriptions = ... CompressionMethod DefaultBlockSize ErrorMethodology MaxBlockSize MaxMediaSize MinBlockSize NeedsCleaning NumberOfMediaSupported BytesPerSector = 512 FirmwareRevision = \"P9CR40D\" Index = 0 InterfaceType = \"SCSI\" Manufacturer = \"(Standard disk drives)\" MediaLoaded = True MediaType = \"Fixed hard disk media\" Model = \"CT2000P3PSSD8\" Partitions = 3 SCSIBus = 0 SCSILogicalUnit = 0 SCSIPort = 0 SCSITargetId = 0 SectorsPerTrack = 63 SerialNumber = \"6479_A78C_A000_000E.\" Signature Size = 2000396321280 TotalCylinders = 243201 TotalHeads = 255 TotalSectors = 3907024065 TotalTracks = 62016255 TracksPerCylinder = 255",
      "CimSystemProperties": "Microsoft.Management.Infrastructure.CimSystemProperties",
      "Caption": "CT2000P3PSSD8",
      "Description": "Disk drive",
      "InstallDate": null,
      "Name": "\\\\.\\PHYSICALDRIVE0",
      "Status": "OK",
      "Availability": null,
      "ConfigManagerErrorCode": 0,
      "ConfigManagerUserConfig": false,
      "CreationClassName": "Win32_DiskDrive",
      "DeviceID": "\\\\.\\PHYSICALDRIVE0",
      "ErrorCleared": null,
      "ErrorDescription": null,
      "LastErrorCode": null,
      "PNPDeviceID": "SCSI\\DISK&VEN_NVME&PROD_CT2000P3PSSD8\\5&1B0B0913&0&000000",
      "PowerManagementCapabilities": null,
      "PowerManagementSupported": null,
      "StatusInfo": null,
      "SystemCreationClassName": "Win32_ComputerSystem",
      "SystemName": "UVMINIAX",
      "Capabilities": "3 4",
      "CapabilityDescriptions": "Random Access Supports Writing",
      "CompressionMethod": null,
      "DefaultBlockSize": null,
      "ErrorMethodology": null,
      "MaxBlockSize": null,
      "MaxMediaSize": null,
      "MinBlockSize": null,
      "NeedsCleaning": null,
      "NumberOfMediaSupported": null,
      "BytesPerSector": 512,
      "FirmwareRevision": "P9CR40D",
      "Index": 0,
      "InterfaceType": "SCSI",
      "Manufacturer": "(Standard disk drives)",
      "MediaLoaded": true,
      "MediaType": "Fixed hard disk media",
      "Model": "CT2000P3PSSD8",
      "Partitions": 3,
      "SCSIBus": 0,
      "SCSILogicalUnit": 0,
      "SCSIPort": 0,
      "SCSITargetId": 0,
      "SectorsPerTrack": 63,
      "SerialNumber": "6479_A78C_A000_000E.",
      "Signature": null,
      "Size": 2000396321280,
      "TotalCylinders": 243201,
      "TotalHeads": 255,
      "TotalSectors": 3907024065,
      "TotalTracks": 62016255,
      "TracksPerCylinder": 255,
      "PSComputerName": null
    },
    {
      "CimClass": "root/cimv2:Win32_DiskDrive",
      "CimInstanceProperties": "Caption = \"Generic STORAGE DEVICE USB Device\" Description = \"Disk drive\" InstallDate Name = \"\\\\.\\PHYSICALDRIVE2\" Status = \"OK\" Availability ConfigManagerErrorCode = 0 ConfigManagerUserConfig = False CreationClassName = \"Win32_DiskDrive\" DeviceID = \"\\\\.\\PHYSICALDRIVE2\" ErrorCleared ErrorDescription LastErrorCode PNPDeviceID = \"USBSTOR\\DISK&VEN_GENERIC&PROD_STORAGE_D... PowerManagementCapabilities PowerManagementSupported StatusInfo SystemCreationClassName = \"Win32_ComputerSystem\" SystemName = \"UVMINIAX\" Capabilities CapabilityDescriptions CompressionMethod DefaultBlockSize ErrorMethodology MaxBlockSize MaxMediaSize MinBlockSize NeedsCleaning NumberOfMediaSupported BytesPerSector FirmwareRevision = \"1532\" Index = 2 InterfaceType = \"USB\" Manufacturer = \"(Standard disk drives)\" MediaLoaded = True MediaType Model = \"Generic STORAGE DEVICE USB Device\" Partitions = 0 SCSIBus = 0 SCSILogicalUnit = 1 SCSIPort = 0 SCSITargetId = 0 SectorsPerTrack SerialNumber = \"000000001532\" Signature = 0 Size TotalCylinders TotalHeads TotalSectors TotalTracks TracksPerCylinder",
      "CimSystemProperties": "Microsoft.Management.Infrastructure.CimSystemProperties",
      "Caption": "Generic STORAGE DEVICE USB Device",
      "Description": "Disk drive",
      "InstallDate": null,
      "Name": "\\\\.\\PHYSICALDRIVE2",
      "Status": "OK",
      "Availability": null,
      "ConfigManagerErrorCode": 0,
      "ConfigManagerUserConfig": false,
      "CreationClassName": "Win32_DiskDrive",
      "DeviceID": "\\\\.\\PHYSICALDRIVE2",
      "ErrorCleared": null,
      "ErrorDescription": null,
      "LastErrorCode": null,
      "PNPDeviceID": "USBSTOR\\DISK&VEN_GENERIC&PROD_STORAGE_DEVICE&REV_1532\\000000001532&1",
      "PowerManagementCapabilities": null,
      "PowerManagementSupported": null,
      "StatusInfo": null,
      "SystemCreationClassName": "Win32_ComputerSystem",
      "SystemName": "UVMINIAX",
      "Capabilities": null,
      "CapabilityDescriptions": null,
      "CompressionMethod": null,
      "DefaultBlockSize": null,
      "ErrorMethodology": null,
      "MaxBlockSize": null,
      "MaxMediaSize": null,
      "MinBlockSize": null,
      "NeedsCleaning": null,
      "NumberOfMediaSupported": null,
      "BytesPerSector": null,
      "FirmwareRevision": "1532",
      "Index": 2,
      "InterfaceType": "USB",
      "Manufacturer": "(Standard disk drives)",
      "MediaLoaded": true,
      "MediaType": null,
      "Model": "Generic STORAGE DEVICE USB Device",
      "Partitions": 0,
      "SCSIBus": 0,
      "SCSILogicalUnit": 1,
      "SCSIPort": 0,
      "SCSITargetId": 0,
      "SectorsPerTrack": null,
      "SerialNumber": "000000001532",
      "Signature": 0,
      "Size": null,
      "TotalCylinders": null,
      "TotalHeads": null,
      "TotalSectors": null,
      "TotalTracks": null,
      "TracksPerCylinder": null,
      "PSComputerName": null
    },
    {
      "CimClass": "root/cimv2:Win32_DiskDrive",
      "CimInstanceProperties": "Caption = \"JMICRON JMS576 USB Device\" Description = \"Disk drive\" InstallDate Name = \"\\\\.\\PHYSICALDRIVE7\" Status = \"OK\" Availability ConfigManagerErrorCode = 0 ConfigManagerUserConfig = False CreationClassName = \"Win32_DiskDrive\" DeviceID = \"\\\\.\\PHYSICALDRIVE7\" ErrorCleared ErrorDescription LastErrorCode PNPDeviceID = \"USBSTOR\\DISK&VEN_JMICRON&PROD_JMS576&RE... PowerManagementCapabilities PowerManagementSupported StatusInfo SystemCreationClassName = \"Win32_ComputerSystem\" SystemName = \"UVMINIAX\" Capabilities = ... CapabilityDescriptions = ... CompressionMethod DefaultBlockSize ErrorMethodology MaxBlockSize MaxMediaSize MinBlockSize NeedsCleaning NumberOfMediaSupported BytesPerSector = 512 FirmwareRevision Index = 7 InterfaceType = \"USB\" Manufacturer = \"(Standard disk drives)\" MediaLoaded = False MediaType = \"External hard disk media\" Model = \"JMICRON JMS576 USB Device\" Partitions SCSIBus = 0 SCSILogicalUnit = 0 SCSIPort = 0 SCSITargetId = 0 SectorsPerTrack = 0 SerialNumber = \"152D00576000\" Signature Size = 0 TotalCylinders = 0 TotalHeads = 0 TotalSectors = 0 TotalTracks = 0 TracksPerCylinder = 0",
      "CimSystemProperties": "Microsoft.Management.Infrastructure.CimSystemProperties",
      "Caption": "JMICRON JMS576 USB Device",
      "Description": "Disk drive",
      "InstallDate": null,
      "Name": "\\\\.\\PHYSICALDRIVE7",
      "Status": "OK",
      "Availability": null,
      "ConfigManagerErrorCode": 0,
      "ConfigManagerUserConfig": false,
      "CreationClassName": "Win32_DiskDrive",
      "DeviceID": "\\\\.\\PHYSICALDRIVE7",
      "ErrorCleared": null,
      "ErrorDescription": null,
      "LastErrorCode": null,
      "PNPDeviceID": "USBSTOR\\DISK&VEN_JMICRON&PROD_JMS576&REV_\\152D00576000&0",
      "PowerManagementCapabilities": null,
      "PowerManagementSupported": null,
      "StatusInfo": null,
      "SystemCreationClassName": "Win32_ComputerSystem",
      "SystemName": "UVMINIAX",
      "Capabilities": "3 4",
      "CapabilityDescriptions": "Random Access Supports Writing",
      "CompressionMethod": null,
      "DefaultBlockSize": null,
      "ErrorMethodology": null,
      "MaxBlockSize": null,
      "MaxMediaSize": null,
      "MinBlockSize": null,
      "NeedsCleaning": null,
      "NumberOfMediaSupported": null,
      "BytesPerSector": 512,
      "FirmwareRevision": null,
      "Index": 7,
      "InterfaceType": "USB",
      "Manufacturer": "(Standard disk drives)",
      "MediaLoaded": false,
      "MediaType": "External hard disk media",
      "Model": "JMICRON JMS576 USB Device",
      "Partitions": null,
      "SCSIBus": 0,
      "SCSILogicalUnit": 0,
      "SCSIPort": 0,
      "SCSITargetId": 0,
      "SectorsPerTrack": 0,
      "SerialNumber": "152D00576000",
      "Signature": null,
      "Size": 0,
      "TotalCylinders": 0,
      "TotalHeads": 0,
      "TotalSectors": 0,
      "TotalTracks": 0,
      "TracksPerCylinder": 0,
      "PSComputerName": null
    },
    {
      "CimClass": "root/cimv2:Win32_DiskDrive",
      "CimInstanceProperties": "Caption = \"WD My Passport 261B SCSI Disk Device\" Description = \"Disk drive\" InstallDate Name = \"\\\\.\\PHYSICALDRIVE3\" Status = \"OK\" Availability ConfigManagerErrorCode = 0 ConfigManagerUserConfig = False CreationClassName = \"Win32_DiskDrive\" DeviceID = \"\\\\.\\PHYSICALDRIVE3\" ErrorCleared ErrorDescription LastErrorCode PNPDeviceID = \"SCSI\\DISK&VEN_WD&PROD_MY_PASSPORT_261B\\... PowerManagementCapabilities PowerManagementSupported StatusInfo SystemCreationClassName = \"Win32_ComputerSystem\" SystemName = \"UVMINIAX\" Capabilities = ... CapabilityDescriptions = ... CompressionMethod DefaultBlockSize ErrorMethodology MaxBlockSize MaxMediaSize MinBlockSize NeedsCleaning NumberOfMediaSupported BytesPerSector = 512 FirmwareRevision = \"3005\" Index = 3 InterfaceType = \"SCSI\" Manufacturer = \"(Standard disk drives)\" MediaLoaded = True MediaType = \"External hard disk media\" Model = \"WD My Passport 261B SCSI Disk Device\" Partitions = 1 SCSIBus = 0 SCSILogicalUnit = 0 SCSIPort = 1 SCSITargetId = 0 SectorsPerTrack = 63 SerialNumber = \"191214400443    \" Signature Size = 1000202273280 TotalCylinders = 121601 TotalHeads = 255 TotalSectors = 1953520065 TotalTracks = 31008255 TracksPerCylinder = 255",
      "CimSystemProperties": "Microsoft.Management.Infrastructure.CimSystemProperties",
      "Caption": "WD My Passport 261B SCSI Disk Device",
      "Description": "Disk drive",
      "InstallDate": null,
      "Name": "\\\\.\\PHYSICALDRIVE3",
      "Status": "OK",
      "Availability": null,
      "ConfigManagerErrorCode": 0,
      "ConfigManagerUserConfig": false,
      "CreationClassName": "Win32_DiskDrive",
      "DeviceID": "\\\\.\\PHYSICALDRIVE3",
      "ErrorCleared": null,
      "ErrorDescription": null,
      "LastErrorCode": null,
      "PNPDeviceID": "SCSI\\DISK&VEN_WD&PROD_MY_PASSPORT_261B\\8&3BD5113&0&000000",
      "PowerManagementCapabilities": null,
      "PowerManagementSupported": null,
      "StatusInfo": null,
      "SystemCreationClassName": "Win32_ComputerSystem",
      "SystemName": "UVMINIAX",
      "Capabilities": "3 4",
      "CapabilityDescriptions": "Random Access Supports Writing",
      "CompressionMethod": null,
      "DefaultBlockSize": null,
      "ErrorMethodology": null,
      "MaxBlockSize": null,
      "MaxMediaSize": null,
      "MinBlockSize": null,
      "NeedsCleaning": null,
      "NumberOfMediaSupported": null,
      "BytesPerSector": 512,
      "FirmwareRevision": "3005",
      "Index": 3,
      "InterfaceType": "SCSI",
      "Manufacturer": "(Standard disk drives)",
      "MediaLoaded": true,
      "MediaType": "External hard disk media",
      "Model": "WD My Passport 261B SCSI Disk Device",
      "Partitions": 1,
      "SCSIBus": 0,
      "SCSILogicalUnit": 0,
      "SCSIPort": 1,
      "SCSITargetId": 0,
      "SectorsPerTrack": 63,
      "SerialNumber": "191214400443    ",
      "Signature": null,
      "Size": 1000202273280,
      "TotalCylinders": 121601,
      "TotalHeads": 255,
      "TotalSectors": 1953520065,
      "TotalTracks": 31008255,
      "TracksPerCylinder": 255,
      "PSComputerName": null
    }
  ]
}
